dsws/__init__.py
dsws/duct.py
dsws/ws_saspy.py
dsws/ws_sqlalchemy.py
dsws-0.49.dist-info/LICENSE
dsws-0.49.dist-info/METADATA
dsws-0.49.dist-info/WHEEL
dsws-0.49.dist-info/top_level.txt
dsws-0.49.dist-info/zip-safe
dsws-0.49.dist-info/RECORD
