Metadata-Version: 2.1
Name: dsws
Version: 0.49
Summary: dsws
Home-page: 
Author: Brad Barker
Author-email: brad@ratiocinate.com
License: MIT
Keywords: Data Science WorkSpace JDBC
Classifier: Programming Language :: Python :: 3.9
Classifier: Topic :: System :: Distributed Computing
Classifier: Topic :: System :: Benchmark
Classifier: Topic :: Database :: Database Engines/Servers
License-File: LICENSE
